yta_editor/__init__.py
yta_editor/media/__init__.py
yta_editor/media/abstract.py
yta_editor/media/audio.py
yta_editor/media/video.py
yta_editor/sources/__init__.py
yta_editor/sources/abstract.py
yta_editor/sources/audio.py
yta_editor/sources/video.py
yta_editor/tests.py
yta_editor/timeline.py
yta_editor/tracks/abstract.py
yta_editor/tracks/audio.py
yta_editor/tracks/items/__init__.py
yta_editor/tracks/items/abstract.py
yta_editor/tracks/items/audio.py
yta_editor/tracks/items/gap.py
yta_editor/tracks/items/transition.py
yta_editor/tracks/items/video.py
yta_editor/tracks/video.py
yta_editor/transformations/__init__.py
yta_editor/transformations/effects/__init__.py
yta_editor/transformations/effects/abstract.py
yta_editor/transformations/effects/audio/__init__.py
yta_editor/transformations/effects/video/__init__.py
yta_editor/transformations/effects/video/brightness.py
yta_editor/transformations/time_based_parameter.py
yta_editor/transformations/transform.py
yta_editor/utils/__init__.py
yta_editor/utils/adapter.py
yta_editor/utils/alpha.py
yta_editor/utils/cache.py
yta_editor/utils/effects.py
yta_editor/utils/frame_combinator.py
yta_editor/utils/frame_generator.py
yta_editor/utils/frame_wrapper.py
yta_editor/utils/silence.py
yta_editor/utils/transition_calculator.py
yta_editor/validation.py
yta_editor-0.2.22.dist-info/licenses/LICENSE
yta_editor-0.2.22.dist-info/METADATA
yta_editor-0.2.22.dist-info/WHEEL
yta_editor-0.2.22.dist-info/RECORD
