Metadata-Version: 2.4
Name: yta-editor
Version: 0.2.22
Summary: Youtube Autonomous Main Editor
License-File: LICENSE
Author: danialcala94
Author-email: danielalcalavalera@gmail.com
Requires-Python: ==3.9
Classifier: Programming Language :: Python :: 3
Classifier: Programming Language :: Python :: 3.9
Requires-Dist: av (>=0.0.1,<99.0.0)
Requires-Dist: numpy (>=0.0.1,<9.0.0)
Requires-Dist: pillow (>=0.0.1,<99.0.0)
Requires-Dist: quicktions (>=0.0.1,<9.0.0)
Requires-Dist: yta_colors (>=0.0.1,<1.0.0)
Requires-Dist: yta_editor_common (>=0.0.1,<1.0.0)
Requires-Dist: yta_editor_nodes (>=0.0.1,<1.0.0)
Requires-Dist: yta_logger (>=0.0.1,<1.0.0)
Requires-Dist: yta_math_progression (>=0.0.1,<1.0.0)
Requires-Dist: yta_numpy (>=0.0.1,<1.0.0)
Requires-Dist: yta_time_interval (>=0.0.1,<1.0.0)
Requires-Dist: yta_timer (>=0.0.1,<1.0.0)
Requires-Dist: yta_validation (>=0.0.1,<1.0.0)
Requires-Dist: yta_video_frame_time (>=0.0.1,<1.0.0)
Requires-Dist: yta_video_pyav (>=0.0.1,<1.0.0)
